playreviews
