Metadata-Version: 1.0
Name: playreviews
Version: 0.3
Summary: Package to scrape google play store reviews
Home-page: https://github.com/sharat9211/playreviews
Author: Sharat Chandra
Author-email: sharat9211@gmail.com
License: UNKNOWN
Keywords: google play store reviews,reviews,play store
Platform: UNKNOWN
